pymarshal/__init__.py
pymarshal/bson.py
pymarshal/csv.py
pymarshal/json.py
pymarshal/util/__init__.py
pymarshal/util/checks.py
pymarshal/util/init_args.py
pymarshal/util/key_swap.py
pymarshal/util/marshal.py
pymarshal/util/pm_assert.py
pymarshal/util/type.py
pymarshal-2.2.3.dist-info/LICENSE
pymarshal-2.2.3.dist-info/METADATA
pymarshal-2.2.3.dist-info/WHEEL
pymarshal-2.2.3.dist-info/top_level.txt
pymarshal-2.2.3.dist-info/RECORD
