Metadata-Version: 2.1
Name: pymarshal
Version: 2.2.3
Summary: Pythonic implementation of Golang struct (un)marshalling
Home-page: https://gitlab.com/d3v-t00Lz/pymarshal
Download-URL: https://gitlab.com/d3v-t00Lz/pymarshal/-/archive/2.2.3/pymarshal-2.2.3.tar.gz
Author: Pymarshal Team
Author-email: pymarshal@noreply.gitlab.com
Keywords: marshal,unmarshal,struct,serialize,serialization,json,bson,csv
License-File: LICENSE
Requires-Dist: bson
Requires-Dist: pyyaml
